README.md
setup.py
django_test_extras.egg-info/PKG-INFO
django_test_extras.egg-info/SOURCES.txt
django_test_extras.egg-info/dependency_links.txt
django_test_extras.egg-info/requires.txt
django_test_extras.egg-info/top_level.txt
test_extras/__init__.py
test_extras/logging.py
test_extras/models.py
test_extras/selenium.py
test_extras/testcases.py
test_extras/testrunners.py
test_extras/tests.py
test_extras/webdriverplus.py
test_extras/management/__init__.py
test_extras/management/commands/__init__.py
test_extras/management/commands/test.py