Metadata-Version: 1.0
Name: django-test-extras
Version: 4.0.0
Summary: Enhancements for the Django test command and testing utility code
Home-page: http://github.com/brightinteractive/django-test-extras/
Author: Bright Interactive
Author-email: admin@bright-interactive.co.uk
License: BSD
Platform: UNKNOWN
